python_domains-0.1.0.dist-info/DESCRIPTION.rst
python_domains-0.1.0.dist-info/METADATA
python_domains-0.1.0.dist-info/metadata.json
python_domains-0.1.0.dist-info/top_level.txt
python_domains-0.1.0.dist-info/WHEEL
python_domains-0.1.0.dist-info/RECORD
domains/__init__.py
domains/core.py
