Metadata-Version: 2.0
Name: python-domains
Version: 0.1.0
Summary: Domain name utilities
Home-page: https://github.com/mrkschan/python-domains
Author: mrkschan
Author-email: mrkschan@gmail.com
License: UNKNOWN
Download-URL: https://github.com/mrkschan/python-domains
Platform: UNKNOWN
Requires-Dist: nose
